MANIFEST.in
README.md
README_CN.md
TODO.md
setup.py
geojson_utils/__init__.py
geojson_utils/convertor.py
geojson_utils/coordTransform_utils.py
geojson_utils/geojson_utils.py
geojson_utils/merger.py
geojson_utils.egg-info/PKG-INFO
geojson_utils.egg-info/SOURCES.txt
geojson_utils.egg-info/dependency_links.txt
geojson_utils.egg-info/top_level.txt
geojson_utils.egg-info/zip-safe