Metadata-Version: 1.1
Name: geojson-utils
Version: 0.0.1
Summary: Python helper functions for manipulating GeoJSON
Home-page: https://github.com/brandonxiang/geojson-python-utils
Author: brandonxiang
Author-email: 1542453460@qq.com
License: MIT
Keywords: python geojson util calculation
Platform: UNKNOWN
Classifier: License :: OSI Approved :: MIT License
Classifier: Programming Language :: Python
Classifier: Intended Audience :: Developers
Classifier: Operating System :: OS Independent
